{
    "code": 0,
    "reason": "",
    "message": "success",
    "data": {
        "history": [
            {
                "maker": "45CpoK9N5CZL6rindWuLmTJC4xPAjqLNSaXj9itEDxBH",
                "base_amount": "1587284.295607",
                "quote_amount": "0.044444619",
                "amount_usd": "6.1289129601",
                "timestamp": 1767849010,
                "event": "buy",
                "tx_hash": "3Svd8JVjYyz88caKe4fCKBnvArGJmHYcpdySsY67Jw2trU6sMY2obmYSoyDATpn7LHBqkzw6yxZetN4Fewm3Pk9P",
                "price_usd": "0.0000038612572285",
                "id": "MzkyMDY0NzE1MDExMDgwMDE=",
                "is_open_or_close": 1,
                "token_address": "GnVYyqYxo9Y6T3Xd24pN9n8vBWACCYcDhgR5dmJ2hood",
                "maker_tags": [],
                "maker_token_tags": [],
                "maker_event_tags": [],
                "quote_address": "So11111111111111111111111111111111111111111",
                "quote_symbol": "",
                "total_trade": 1,
                "balance": "1587284.295607",
                "history_bought_amount": "1587284.295607",
                "history_sold_income": "0",
                "history_sold_amount": "0",
                "realized_profit": "0",
                "unrealized_profit": "0",
                "maker_name": "",
                "maker_twitter_username": "",
                "maker_twitter_name": "",
                "maker_avatar": "",
                "maker_ens": "",
                "priority_fee": "0.000029118",
                "tip_fee": "0.000114621",
                "gas_usd": "",
                "gas_native": "",
                "dex_usd": "",
                "dex_native": ""
            },
            {
                "maker": "F9QE1r1A796i4isGGZVjCwrmvYyC9s1q1rcbP9YWpzP4",
                "base_amount": "288020.020002",
                "quote_amount": "0.008054912",
                "amount_usd": "1.1107723648",
                "timestamp": 1767849006,
                "event": "sell",
                "tx_hash": "3LP4r1YtqqzgMe8V6LAvncghpRuy6fnP4rduoU4jrFmBZFdisywmqBmDCQSHxcnkrcWowt6K1R21MAxRY5c6qJiq",
                "price_usd": "0.00000385658040516",
                "id": "MzkyMDY0NzAzMDAyOTMwMDA=",
                "is_open_or_close": 1,
                "token_address": "GnVYyqYxo9Y6T3Xd24pN9n8vBWACCYcDhgR5dmJ2hood",
                "maker_tags": [],
                "maker_token_tags": [
                    "creator",
                    "top_holder"
                ],
                "maker_event_tags": [],
                "quote_address": "So11111111111111111111111111111111111111112",
                "quote_symbol": "",
                "total_trade": 2,
                "balance": "0",
                "history_bought_amount": "288020.020002",
                "history_sold_income": "1.1107723648",
                "history_sold_amount": "288020.020002",
                "realized_profit": "-0.0301647365",
                "unrealized_profit": "0",
                "maker_name": "",
                "maker_twitter_username": "",
                "maker_twitter_name": "",
                "maker_avatar": "",
                "maker_ens": "",
                "priority_fee": "",
                "tip_fee": "",
                "gas_usd": "",
                "gas_native": "",
                "dex_usd": "",
                "dex_native": ""
            },
            {
                "maker": "F9QE1r1A796i4isGGZVjCwrmvYyC9s1q1rcbP9YWpzP4",
                "base_amount": "288020.020002",
                "quote_amount": "0.008054913",
                "amount_usd": "1.11109469922",
                "timestamp": 1767848999,
                "event": "buy",
                "tx_hash": "4zLUapoXnVYzRUswdYYPpinmSti6AWmioaeXFqFkPKNo9zo4K8sVBZ9UtvgAvn4d4DzmvVMVBTEVC3iZPgWTjJRe",
                "price_usd": "0.000003857699547966",
                "id": "MzkyMDY0Njg4MDEzMjIwMDU=",
                "is_open_or_close": 1,
                "token_address": "GnVYyqYxo9Y6T3Xd24pN9n8vBWACCYcDhgR5dmJ2hood",
                "maker_tags": [],
                "maker_token_tags": [
                    "creator",
                    "top_holder"
                ],
                "maker_event_tags": [],
                "quote_address": "So11111111111111111111111111111111111111111",
                "quote_symbol": "",
                "total_trade": 2,
                "balance": "0",
                "history_bought_amount": "288020.020002",
                "history_sold_income": "1.1107723648",
                "history_sold_amount": "288020.020002",
                "realized_profit": "-0.0301647365",
                "unrealized_profit": "0",
                "maker_name": "",
                "maker_twitter_username": "",
                "maker_twitter_name": "",
                "maker_avatar": "",
                "maker_ens": "",
                "priority_fee": "",
                "tip_fee": "",
                "gas_usd": "",
                "gas_native": "",
                "dex_usd": "",
                "dex_native": ""
            }
        ],
        "next": ""
    }
}